{
  "featuredArticleId": "698a5c6c2c6102f180bbc9d7",
  "topStories": [
    {
      "title": "WORLD NEWS",
      "blurb": "Economic policies are shaping international markets",
      "to": "/worldnews",
      "imageUrl": ""
    },
    {
      "title": "TECHNOLOGY",
      "blurb": "The latest trends in AI and innovation",
      "to": "/technology",
      "imageUrl": ""
    },
    {
      "title": "BUSINESS",
      "blurb": "Markets, startups, and policy that shape the economy",
      "to": "/business",
      "imageUrl": ""
    },
    {
      "title": "SPORTS",
      "blurb": "Major updates across the sports world",
      "to": "/sports",
      "imageUrl": "/uploads/hero/stories/1770897025793-218737089.jpg"
    }
  ],
  "featured": {
    "imageUrl": "/uploads/hero/featured/1770822976114-173351161.png",
    "category": "Health",
    "author": "Edgar Kore",
    "date": "Feb 7, 2026",
    "readTime": "9 min read",
    "headline": "Health Foundation & Science",
    "ctaText": "Read Article ->"
  }
}